{
"$meta": {"game_version":"0.9.4.23","class":"mace","hands":1,"crit_bonus":"+25% Daze Chance","source":"https://stoneshard.com/wiki/Maces","page_patch":"0.9.3.0","schema":"data/schema.md"},
"items": [
{"n":"Spiked Club","t":1,"r":"C","d":{"pi":2,"cr":14},"du":60,"p":75,"s":{"ap":15,"bpd":7,"bl":4,"dz":5,"sg":10,"sec":10}},
{"n":"Militia Morgenstern","t":2,"r":"C","d":{"pi":3,"cr":16},"du":80,"p":375,"s":{"ap":15,"bpd":10,"bl":8,"dz":7,"sg":15,"sec":10}},
{"n":"Morgenstern","t":3,"r":"C","d":{"pi":2,"cr":19},"du":100,"p":975,"s":{"ap":20,"bpd":20,"bl":12,"dz":10,"sg":20,"sec":15}},
{"n":"Skadian Bludgeon","t":3,"r":"C","d":{"cr":21},"du":120,"p":1125,"s":{"ap":20,"dz":13,"sg":13,"ce":18,"fum":-5,"sec":15}},
{"n":"Veteran Morgenstern","t":4,"r":"C","d":{"pi":2,"cr":22},"du":120,"p":2175,"s":{"ap":20,"bpd":16,"bl":16,"dz":12,"sg":25,"sec":20}},
{"n":"Druzhyna Bludgeon","t":4,"r":"C","d":{"cr":24},"du":145,"p":2625,"s":{"ap":20,"dz":16,"sg":16,"ce":22,"fum":-6,"sec":20}},
{"n":"Knight Morgenstern","t":5,"r":"C","d":{"pi":3,"cr":25},"du":140,"p":4600,"s":{"ap":25,"bpd":20,"bl":20,"dz":15,"sg":30,"sec":20}},
{"n":"Chervenian Mace","t":5,"r":"C","d":{"cr":28},"du":160,"p":4600,"s":{"ap":25,"dz":20,"sg":20,"ce":26,"fum":-7,"sec":20}},
{"n":"Baron Morgenstern","t":5,"r":"U","d":{"pi":4,"cr":25},"du":135,"p":4600,"s":{"ap":25,"bpd":25,"bl":26,"dz":15,"sg":30,"cc":3,"ce":10,"sec":20}},
{"n":"Voivod Mace","t":5,"r":"U","d":{"cr":28},"du":175,"p":4600,"s":{"ap":33,"dz":20,"st":5,"sg":20,"ce":26,"fum":-7,"er":5,"sec":20,"cd":-5}},
{"n":"Cudgel","t":1,"r":"C","d":{"cr":14},"du":45,"p":25,"s":{"ap":10,"dz":8,"st":4,"kb":5,"co":3,"sec":10}},
{"n":"Reinforced Club","t":1,"r":"C","d":{"cr":15},"du":70,"p":75,"s":{"ap":20,"dz":10,"st":4,"kb":5,"co":3,"sec":10}},
{"n":"Militia Club","t":2,"r":"C","d":{"cr":17},"du":95,"p":375,"s":{"ap":20,"dz":12,"st":7,"kb":11,"co":5,"fum":-2,"sec":10}},
{"n":"Recruit Club","t":2,"r":"C","d":{"cr":17},"du":100,"p":375,"s":{"ap":20,"dz":14,"st":8,"kb":8,"co":4,"sec":10}},
{"n":"Flanged Mace","t":3,"r":"C","d":{"cr":19},"du":120,"p":975,"s":{"ap":25,"dz":16,"st":10,"kb":12,"co":5,"sec":15}},
{"n":"Shishpar","t":3,"r":"C","d":{"cr":19},"du":140,"p":1125,"s":{"ap":25,"ad":10,"dz":18,"st":10,"kb":14,"co":3,"sec":15}},
{"n":"Reinforced Flanged Mace","t":4,"r":"C","d":{"cr":22},"du":150,"p":2175,"s":{"ap":25,"dz":20,"st":13,"kb":16,"co":6,"sec":20}},
{"n":"Bozdogan","t":4,"r":"C","d":{"cr":22},"du":145,"p":2500,"s":{"ap":25,"ad":15,"dz":24,"st":13,"kb":16,"co":4,"sec":20}},
{"n":"Knight Flanged Mace","t":5,"r":"C","d":{"cr":25},"du":170,"p":4600,"s":{"ap":30,"dz":25,"st":15,"kb":20,"co":7,"sec":20}},
{"n":"Noble Flanged Mace","t":5,"r":"C","d":{"cr":25},"du":195,"p":4825,"s":{"ap":30,"bpd":10,"dz":25,"st":15,"kb":20,"co":4,"fum":-1,"sec":20}},
{"n":"Ghazi Flanged Mace","t":5,"r":"U","d":{"cr":24,"sa":1},"du":175,"p":4600,"s":{"ap":30,"ad":5,"dz":33,"st":19,"kb":20,"co":7,"sec":15,"ftr":5}},
{"n":"Ornate Flanged Mace","t":5,"r":"U","d":{"cr":25},"du":160,"p":4600,"s":{"ap":35,"ad":25,"dz":25,"st":15,"kb":25,"sg":25,"co":7,"sec":20}},
{"n":"Footman Warhammer","t":3,"r":"C","d":{"cr":20},"du":110,"p":1075,"s":{"ap":30,"ad":40,"dz":12,"sg":16,"acc":5,"fum":-2,"sec":15}},
{"n":"Brynn Warhammer","t":3,"r":"C","d":{"cr":20},"du":120,"p":1075,"s":{"ap":30,"ad":40,"bl":5,"dz":6,"sg":16,"acc":5,"cc":3,"sec":15}},
{"n":"Chekan","t":3,"r":"C","d":{"cr":20},"du":125,"p":1200,"s":{"ap":33,"ad":46,"bpd":10,"dz":10,"sg":10,"acc":2,"sec":15}},
{"n":"Mercenary Warhammer","t":4,"r":"C","d":{"cr":23},"du":130,"p":2425,"s":{"ap":30,"ad":45,"dz":16,"sg":20,"acc":6,"fum":-3,"sec":20}},
{"n":"Fisted Warhammer","t":4,"r":"C","d":{"cr":23},"du":120,"p":2425,"s":{"ap":35,"ad":45,"dz":21,"sg":24,"acc":6,"sec":20}},
{"n":"Captain Warhammer","t":5,"r":"C","d":{"cr":27},"du":145,"p":5100,"s":{"ap":40,"ad":50,"dz":20,"sg":30,"acc":7,"sec":20}},
{"n":"Knight Warhammer","t":5,"r":"C","d":{"cr":27},"du":155,"p":5100,"s":{"ap":35,"ad":50,"dz":26,"sg":20,"acc":7,"cc":3,"sec":20}},
{"n":"Fish Warhammer","t":5,"r":"C","d":{"cr":27},"du":140,"p":5100,"s":{"ap":35,"ad":50,"dz":20,"st":5,"sg":25,"acc":7,"fum":-4,"sec":20}},
{"n":"Ornate Warhammer","t":5,"r":"U","d":{"cr":27},"du":145,"p":5100,"s":{"ap":35,"ad":56,"bpd":15,"dz":20,"sg":25,"acc":7,"sec":15,"cd":-5}},
{"n":"Peasant Flail","t":1,"r":"C","d":{"cr":18},"du":50,"p":75,"s":{"ap":5,"bpd":5,"dz":6,"sg":10,"acc":-3,"cc":2,"fum":4,"sec":15}},
{"n":"Rebel Flail","t":1,"r":"C","d":{"cr":18},"du":50,"p":75,"s":{"ap":5,"bpd":5,"dz":6,"sg":10,"acc":-2,"cc":3,"fum":6,"sec":15}},
{"n":"Militia Flail","t":2,"r":"C","d":{"cr":20},"du":70,"p":425,"s":{"ap":5,"bpd":7,"dz":10,"sg":15,"acc":-4,"cc":3,"fum":6,"sec":15}},
{"n":"Recruit Flail","t":2,"r":"C","d":{"cr":20},"du":75,"p":425,"s":{"ap":5,"bpd":12,"bl":3,"dz":8,"sg":15,"acc":-5,"cc":3,"fum":8,"sec":15}},
{"n":"Footman Flail","t":3,"r":"C","d":{"pi":2,"cr":21},"du":95,"p":1125,"s":{"ap":10,"bpd":15,"bl":6,"dz":10,"sg":23,"acc":-8,"cc":4,"fum":8,"sec":20}},
{"n":"Vehement Flail","t":3,"r":"C","d":{"cr":22,"sa":1},"du":80,"p":1250,"s":{"ap":10,"bpd":10,"dz":14,"sg":20,"acc":-6,"cc":5,"ce":5,"fum":10,"sec":15,"spec":-5}},
{"n":"Nistrian Flail","t":4,"r":"C","d":{"cr":27},"du":135,"p":2925,"s":{"ap":15,"bpd":12,"dz":23,"sg":25,"acc":-8,"cc":5,"fum":10,"sec":25}},
{"n":"Veteran Flail","t":4,"r":"C","d":{"cr":27},"du":100,"p":2550,"s":{"ap":10,"bpd":18,"bl":7,"dz":13,"sg":29,"acc":-6,"cc":6,"ce":8,"fum":12,"sec":25}},
{"n":"Knight Flail","t":5,"r":"C","d":{"cr":31},"du":120,"p":5350,"s":{"ap":15,"bpd":15,"dz":22,"sg":30,"acc":-10,"cc":6,"fum":12,"sec":25}},
{"n":"Three-Headed Flail","t":5,"r":"C","d":{"pi":3,"cr":28},"du":105,"p":5350,"s":{"ap":15,"bpd":26,"bl":9,"dz":15,"sg":35,"acc":-8,"cc":7,"ce":12,"fum":14,"sec":25}},
{"n":"Elven Flail","t":5,"r":"C","d":{"cr":29},"du":135,"p":5900,"s":{"ap":20,"bpd":15,"dz":25,"st":10,"sg":27,"acc":-10,"cc":3,"fum":12,"sec":25}},
{"n":"Emir Flail","t":5,"r":"U","d":{"cr":31},"du":120,"p":5350,"s":{"ap":15,"bpd":30,"bl":10,"dz":17,"sg":38,"acc":-8,"cc":6,"ce":20,"fum":12,"sec":25}},
{"n":"Grandmaster Flail","t":5,"r":"U","d":{"cr":26,"sa":5},"du":130,"p":5350,"s":{"ap":15,"bpd":15,"dz":25,"sg":25,"acc":-10,"cc":6,"fum":14,"sec":25,"spec":-10,"ed":5}},
{"n":"Iron Bar","t":1,"r":"C","d":{"cr":14},"du":50,"p":5,"s":{"bc":1,"fum":3}},
{"n":"Carpenter Hammer","t":1,"r":"C","d":{"cr":15},"du":40,"p":25,"s":{"ap":3,"sg":3,"fum":2}},
{"n":"Blacksmith Hammer","t":1,"r":"C","d":{"cr":17},"du":60,"p":50,"s":{"ap":5,"dz":3,"fum":1}}
]}
