{
 "$meta": {
  "tree": "Shields",
  "cat": "weapon",
  "page_patch": "0.9.3.9",
  "focus": "Survivability, Crowd Control",
  "source": "https://stoneshard.com/wiki/Shields_(skill_tree)",
  "desc_note": "VERBATIM game data (0.9.4.x). Block-Power-derived numbers shown as text (depend on equipped shield)."
 },
 "skills": [
  {
   "n": "Raise Shield",
   "t": 1,
   "type": "Maneuver",
   "target": "No Target",
   "range": 1,
   "en": 8,
   "cd": 10,
   "mod": [
    "str",
    "agi",
    "vit"
   ],
   "req": "shield",
   "desc": "'Raise Shield' 3 turns: +10% Block Chance (scales with shield's Block Chance), +15% Max Block Power, +20% Crit Avoidance, -200% Dodge. Light shield: +20% BP refill, +10% Counter, no Dodge penalty. Heavy: +33% Energy Restoration.",
   "fx": {
    "buff": true,
    "bc": 10,
    "cav": 20
   },
   "dyn": "Activates \"Raise Shield\" for 3 turns:\n+10% Block Chance (+ (AGL + VIT) × shield's Block Chance ÷ 100)\n+{-5+STR+VIT}% Max Block Power\n+{AGL+PRC}% Crit Avoidance\n-200% Dodge Chance\n\nIf equipped with a light shield, replenishes {2*VIT}% Max Block Power, grants the effect +{5+0.5*AGL}% Counter Chance, and doesn't penalize Dodge Chance.\n\nIf equipped with a heavy shield, grants the effect +33% Energy Restoration."
  },
  {
   "n": "Embodiment of Resilience",
   "t": 1,
   "type": "Passive",
   "mod": [
    "wil"
   ],
   "req": "shield",
   "desc": "Full blocks: +5% Max Energy, tree cooldowns -2. Partial blocks: -5% Damage Taken 6 turns (x2).",
   "dyn": "Full blocks replenish {-5+WIL}% Max Energy and reduce the ability tree's cooldowns by 2 turns.\n\nPartial blocks grant -5% Damage Taken for 6 turns.\n\nThe effect stacks up to 2 times."
  },
  {
   "n": "Breakthrough",
   "t": 1,
   "type": "Maneuver",
   "target": "Target Area",
   "range": 1,
   "en": 16,
   "cd": 14,
   "mod": [
    "str",
    "prc",
    "vit"
   ],
   "req": "shield",
   "desc": "6 Crushing to 3 adjacent tiles, 85% Accuracy, 80% Stagger. Hits: target -20% Control Res, -25% Move Res 6 turns; +5% BP Recovery 3 turns and tree cooldowns -2 per enemy in area. Light shield: -25% CD. Heavy: hits +10% Damage Taken 6 turns.",
   "dyn": "Deals Crushing Damage to three adjacent tiles ((6 + 25% of Max Block Power) × shield condition) with {65+2*PRC}% Accuracy, Crit Chance equal to 10% of Block Chance, and {60+2*STR}% Stagger Chance.\n\nHitting a target applies it with -20% Control Resistance and -25% Move Resistance for 6 turns.\n\nGrants +{0.5*VIT}% Block Power Recovery for 3 turns and reduces the ability tree's cooldowns by 2 turns for each enemy within the skill's area of effect.\n\nIf equipped with a light shield, grants the skill -25% Cooldown Duration.\n\nIf equipped with a heavy shield, hitting a target applies it with +10% Damage Taken for 6 turns (the effect stacks up to 2 times)."
  },
  {
   "n": "Moment of Retribution",
   "t": 1,
   "type": "Passive",
   "req": "shield",
   "desc": "Using the ability tree's skills grants +5% Weapon Damage and +4% Counter Chance for 5 turns.\n\nThe effect stacks up to 3 times.\n\nDamaging counters replenish 5% Max Block Power.",
   "fx": {
    "buff": true,
    "stacks": 3,
    "per_stack": {
     "wd": 5,
     "co": 4
    }
   }
  },
  {
   "n": "Last Bastion",
   "t": 2,
   "type": "Passive",
   "req": "shield",
   "desc": "Grants +3% Block Power Recovery for 6 turns for each adjacent enemy.\n\nEach received hit grants +3% Energy Restoration for 6 turns.\n\nBoth effects stack up to 5 times.\n\nIf equipped with a light shield, both effects trigger twice per turn."
  },
  {
   "n": "Shield Bash",
   "t": 2,
   "type": "Maneuver",
   "target": "Target Object",
   "range": 1,
   "en": 16,
   "cd": 12,
   "mod": [
    "str",
    "prc",
    "vit"
   ],
   "req": "shield",
   "desc": "8 Crushing, 100% Accuracy, 40% Daze, 80% Knockback. Replenishes 15% Max Block Power. Light shield: -25% CD. Heavy: BP refill = 30% of damage.",
   "dyn": "Deals Crushing Damage ((8 + 30% of Max Block Power) × shield condition) with {80+2*PRC}% Accuracy, Crit Chance equal to 20% of Block Chance, {2*AGL+2*PRC}% Daze Chance, and {60+2*STR}% Knockback Chance.\n\nReplenishes {-5+2*VIT}% Max Block Power.\n\nIf equipped with a light shield, grants the skill -25% Cooldown Duration.\n\nIf equipped with a heavy shield, replenishes Block Power for 30% of the damage dealt."
  },
  {
   "n": "Hold the Line!",
   "t": 3,
   "type": "Maneuver",
   "target": "No Target",
   "range": 1,
   "en": 14,
   "cd": 14,
   "req": "shield",
   "desc": "Activates \"Hold the Line!\" for 10 turns:\n-5% Damage Taken\n+5% Block Power Recovery\n+7% Counter Chance\n+10% Move Resistance\n+10% Control Resistance\n\nUsing the ability tree's skills grants 2 stacks of the effect (up to IV) but reduces its duration by 1 turn.\n\nEach received hit prolongs the effect's duration by 1 turn (up to 10) but reduces its number of stacks (no more than once per turn).\n\nIf equipped with a light shield, grants the skill -25% Cooldown Duration.\n\nIf equipped with a heavy shield, grants an extra stack of the effect upon activation.",
   "fx": {
    "buff": true,
    "per_stack": {
     "dt": -5,
     "bpr": 5,
     "co": 7,
     "mvr": 10,
     "ctr": 10
    },
    "stacks": 4
   }
  },
  {
   "n": "Retaliation",
   "t": 3,
   "type": "Passive",
   "req": "shield",
   "desc": "Grants \"Shield Bash\" and \"Breakthrough\" +50% Damage and increases their Crit Chance by half.\n\nUsing these skills applies the target with -10% Accuracy, -10% Counter Chance, and -15% Weapon Damage for 5 turns.\n\nThe effect stacks up to 2 times.",
   "fx": {
    "buff": true,
    "stacks": 2,
    "per_stack": {
     "cc": 50
    }
   }
  }
 ]
}